kaifario/__init__.py
kaifario/builder.py
kaifario/configuration.py
kaifario/protocols/__init__.py
kaifario/protocols/loader.py
kaifario/protocols/provider.py
kaifario/providers/__init__.py
kaifario/providers/enviroment.py
kaifario/providers/ini.py
kaifario/providers/json_provider.py
kaifario/providers/memory.py
kaifario/providers/toml.py
kaifario/providers/yaml.py
kaifario-0.3.1.dist-info/licenses/LICENSE
kaifario-0.3.1.dist-info/METADATA
kaifario-0.3.1.dist-info/WHEEL
kaifario-0.3.1.dist-info/top_level.txt
kaifario-0.3.1.dist-info/RECORD
