Metadata-Version: 2.4
Name: kaifario
Version: 0.3.1
Summary: Configuration providing library
Author-email: Kurosawa <145038102+KurosawaAngel@users.noreply.github.com>
License: MIT
Classifier: Programming Language :: Python :: 3.11
Classifier: Programming Language :: Python :: 3.12
Classifier: Programming Language :: Python :: 3.13
Classifier: Topic :: Software Development :: Libraries
Classifier: Typing :: Typed
Classifier: Intended Audience :: Developers
Classifier: License :: OSI Approved :: MIT License
Classifier: Operating System :: OS Independent
Requires-Python: >=3.11
License-File: LICENSE
Requires-Dist: adaptix>=3.0.0b9
Provides-Extra: yaml
Requires-Dist: pyyaml>=6.0; extra == "yaml"
Dynamic: license-file
